notes/__init__.py
notes/adapters.py
notes/bh_cli.py
notes/bh_llm.py
notes/cli.py
notes/config.py
notes/costs.py
notes/datamodel.py
notes/graph.py
notes/providers_openai.py
notes/search.py
notes/storage.py
notes/streams.py
notes/tags.py
notes/transcription.py
notes/bh/__init__.py
notes/bh/app.py
notes/bh/db.py
notes/bh/ingestion.py
notes/bh/state.py
notes/migrations/__init__.py
notes/migrations/reintegrate.py
znotes-0.8.1.dist-info/METADATA
znotes-0.8.1.dist-info/WHEEL
znotes-0.8.1.dist-info/entry_points.txt
znotes-0.8.1.dist-info/top_level.txt
znotes-0.8.1.dist-info/RECORD
